<LanguageData>
  
  
  <ChildInLaw.label>ﺲﻳﺮﻋ</ChildInLaw.label>
  
  <ChildInLaw.labelFemale>ﺓﺮﻴﻐﺼﻟﺍ ﺔﺟﻭﺰﻟﺍ</ChildInLaw.labelFemale>
  
  
  <ExLover.label>ﻖﺑﺎﺳ</ExLover.label>
  <ExLover.labelFemale>ﺔﻘﺑﺎﺴﻟﺍ</ExLover.labelFemale>
  
  
  <ExSpouse.label>ﻖﺑﺎﺴﻟﺍ ﺝﻭﺰﻟﺍ</ExSpouse.label>
  
  <ExSpouse.labelFemale>ﺔﻘﺑﺎﺴﻟﺍ ﺔﺟﻭﺰﻟﺍ</ExSpouse.labelFemale>
  
  
  <Fiance.label>ﺲﻳﺮﻌﻟﺍ</Fiance.label>
  
  <Fiance.labelFemale>ﺱﻭﺮﻌﻟﺍ</Fiance.labelFemale>
  
  
  <Lover.label>ﻖﻴﺸﻌﻟﺍ</Lover.label>
  <Lover.labelFemale>ﺔﻘﻴﺸﻌﻟﺍ</Lover.labelFemale>
  
  
  <ParentInLaw.label>ﻥﺍﻮﺑﻷﺍ</ParentInLaw.label>
  
  <ParentInLaw.labelFemale>ﺓﺎﻤﺤﻟﺍ</ParentInLaw.labelFemale>
  
  
  <Spouse.label>ﺝﻭﺯ</Spouse.label>
  
  <Spouse.labelFemale>ﺔﺟﻭﺰﻟﺍ</Spouse.labelFemale>
  
  
  <Stepchild.label>ﻲﺟﻭﺰﻟﺍ ﻦﺑﻻﺍ</Stepchild.label>
  
  <Stepchild.labelFemale>ﺔﺟﻭﺰﻟﺍ/ﺝﻭﺰﻟﺍ ﺔﻨﺑﺍ</Stepchild.labelFemale>
  
  
  <Stepparent.label>ﻲﻧﺎﺜﻟﺍ ﺝﻭﺰﻟﺍ</Stepparent.label>
  
  <Stepparent.labelFemale>ﺔﻴﻧﺎﺜﻟﺍ ﺔﺟﻭﺰﻟﺍ</Stepparent.labelFemale>
  
</LanguageData>